acme_dns_azure/___init___.py
acme_dns_azure/certbot_manager.py
acme_dns_azure/client.py
acme_dns_azure/config/__init__.py
acme_dns_azure/config/schema.py
acme_dns_azure/context/__init__.py
acme_dns_azure/data.py
acme_dns_azure/dns_validation.py
acme_dns_azure/exceptions.py
acme_dns_azure/key_vault_manager.py
acme_dns_azure/log/__init__.py
acme_dns_azure/os_manager.py
acme_dns_azure-0.4.0.dist-info/LICENSE
acme_dns_azure-0.4.0.dist-info/METADATA
acme_dns_azure-0.4.0.dist-info/WHEEL
acme_dns_azure-0.4.0.dist-info/entry_points.txt
acme_dns_azure-0.4.0.dist-info/RECORD
