Metadata-Version: 2.1
Name: acme-dns-azure
Version: 0.4.0
Summary: ACME client setup based on Certbot for dns-01 challenges via Azure Cloud services
Home-page: https://github.com/ZEISS/acme-dns-azure
License: MIT
Keywords: acme,dns,azure,certbot,letsencrypt
Author: ZEISS Digital Innovation Partners
Requires-Python: >=3.8,<4.0
Classifier: Development Status :: 5 - Production/Stable
Classifier: Intended Audience :: Developers
Classifier: Intended Audience :: System Administrators
Classifier: License :: OSI Approved :: MIT License
Classifier: Programming Language :: Python :: 3
Classifier: Programming Language :: Python :: 3.8
Classifier: Programming Language :: Python :: 3.9
Classifier: Programming Language :: Python :: 3.10
Classifier: Programming Language :: Python :: 3.11
Classifier: Programming Language :: Python :: 3.12
Classifier: Programming Language :: Python :: 3.7
Classifier: Topic :: Internet :: Name Service (DNS)
Classifier: Topic :: Software Development :: Libraries :: Python Modules
Classifier: Topic :: System :: Installation/Setup
Classifier: Topic :: System :: Systems Administration
Classifier: Topic :: Utilities
Requires-Dist: azure-identity (>=1.14.0)
Requires-Dist: azure-keyvault-certificates (>=4.7.0)
Requires-Dist: azure-keyvault-secrets (>=4.7.0)
Requires-Dist: certbot (>=2)
Requires-Dist: certbot-dns-azure (>=2.5.0)
Requires-Dist: cryptography (>=42.0.0)
Requires-Dist: dnspython (>=2)
Requires-Dist: pyyaml (>=3)
Requires-Dist: requests (>=2)
Requires-Dist: strictyaml (>=1.7.3)
Project-URL: Documentation, https://zeiss.github.io/acme-dns-azure/
Project-URL: PyPI, https://pypi.org/project/acme-dns-azure/
Project-URL: Repository, https://github.com/ZEISS/acme-dns-azure
